python_textops-0.3.6.dist-info/DESCRIPTION.rst
python_textops-0.3.6.dist-info/METADATA
python_textops-0.3.6.dist-info/RECORD
python_textops-0.3.6.dist-info/WHEEL
python_textops-0.3.6.dist-info/eager_resources.txt
python_textops-0.3.6.dist-info/metadata.json
python_textops-0.3.6.dist-info/top_level.txt
textops/__init__.py
textops/base.py
textops/ops/__init__.py
textops/ops/cast.py
textops/ops/fileops.py
textops/ops/listops.py
textops/ops/parse.py
textops/ops/recode.py
textops/ops/runops.py
textops/ops/strops.py
textops/ops/wrapops.py
