Metadata-Version: 2.0
Name: python-textops
Version: 0.3.6
Summary: Python text operations module
Home-page: https://github.com/elapouya/python-textops
Author: Eric Lapouyade
Author-email: elapouya@gmail.com
License: LGPL 2.1
Keywords: textops
Platform: UNKNOWN
Classifier: Intended Audience :: Developers
Classifier: Development Status :: 4 - Beta
Classifier: Programming Language :: Python :: 2
Classifier: Programming Language :: Python :: 2.7
Classifier: Programming Language :: Python :: 2.6
Requires-Dist: Sphinx
Requires-Dist: sphinxcontrib-napoleon
Requires-Dist: addicted
Requires-Dist: python-dateutil
Requires-Dist: python-slugify
